Metadata-Version: 2.1
Name: HEXaag
Version: 1.0.0
Summary: Ferramenta para gerar grid de hexágonos, para a criação de mapas de RPG.
Author: Alessandro Guarita
Requires-Python: >=3.11
License-File: LICENSE
